{
    "@odata.context": "/redfish/v1/$metadata#LogEntry.LogEntry",
    "@odata.etag": "W/\"E36CC7DD\"",
    "@odata.id": "/redfish/v1/Systems/1/LogServices/Event/Entries/59",
    "@odata.type": "#LogEntry.v1_11_0.LogEntry",
    "Id": "59",
    "Created": "2023-02-16T12:03:37Z",
    "EntryType": "Oem",
    "EventId": "1a3f0162-5305-4337-bdf5-cf465c1d8493",
    "EventTimestamp": "2023-02-16T12:03:37Z",
    "Links": {
        "OriginOfCondition": {
            "@odata.id": "/redfish/v1/Systems/1"
        }
    },
    "MessageArgs": [
        "NoAMS",
        "vMainDeviceDiscoveryComplete",
        "Complete"
    ],
    "MessageId": "iLOEvents.3.8.DeviceDiscoveryStatusV2",
    "Name": "Event",
    "OemRecordFormat": "Hpe-Event",
    "Severity": "OK"
}