{
    "@odata.context": "/redfish/v1/$metadata#LogEntry.LogEntry",
    "@odata.etag": "W/\"C50E588B\"",
    "@odata.id": "/redfish/v1/Systems/1/LogServices/Event/Entries/153",
    "@odata.type": "#LogEntry.v1_11_0.LogEntry",
    "Id": "153",
    "Created": "2023-02-16T17:30:41Z",
    "EntryType": "Oem",
    "EventId": "d05f9d8c-0230-fd5a-7822-8274184325c3",
    "EventTimestamp": "2023-02-16T17:30:41Z",
    "Links": {
        "OriginOfCondition": {
            "@odata.id": "/redfish/v1/Systems/1"
        }
    },
    "MessageArgs": [
        "NoAMS",
        "Busy",
        "Complete"
    ],
    "MessageId": "iLOEvents.3.8.DeviceDiscoveryStatusV2",
    "Name": "Event",
    "OemRecordFormat": "Hpe-Event",
    "Severity": "OK"
}